RTL/synchronize.v
// synchronizes


module synchronizer #(
    parameter WIDTH = 4
)(
    input wire clk, 
    input wire rst_n, 
    input wire [WIDTH-1:0] async_in, 
    output reg [WIDTH-1:0] sync_out
);
    
    reg [WIDTH-1:0] q1;

    always @(posedge clk or negedge rst_n) begin
        if (!rst_n) begin
            q1 <= 0;
            sync_out <= 0;
        end else begin
            q1 <= async_in;
            sync_out <= q1;
        end
    end
endmodule

RTL/read_ptr.v

module read_handler #(
    parameter DEPTH = 16,
    parameter ADDR_WIDTH = $clog2(DEPTH)
)(
    input wire rclk, 
    input wire rrst_n, 
    input wire r_en, 
    input wire [ADDR_WIDTH:0] g_wptr_sync, 
    
    output wire [ADDR_WIDTH-1:0] b_raddr,  
    output reg [ADDR_WIDTH:0] g_rptr,      
    output reg empty // <-- CHANGED: Now a registered output
);

    reg  [ADDR_WIDTH:0] b_rptr;
    wire [ADDR_WIDTH:0] b_rptr_next;
    wire [ADDR_WIDTH:0] g_rptr_next;
    wire empty_next; // <-- ADDED: Combinational empty calculation

    // Binary next state
    assign b_rptr_next = b_rptr + (r_en & ~empty);
    
    // Binary to Gray conversion
    assign g_rptr_next = (b_rptr_next >> 1) ^ b_rptr_next;

    // Empty condition (Calculated combinationally based on next pointer)
    assign empty_next = (g_rptr_next == g_wptr_sync);

    always @(posedge rclk or negedge rrst_n) begin
        if (!rrst_n) begin
            b_rptr <= 0;
            g_rptr <= 0;
            empty  <= 1'b1; // <-- ADDED: Initialize empty flag to 1!
        end else begin
            b_rptr <= b_rptr_next;
            g_rptr <= g_rptr_next;
            empty  <= empty_next; // <-- ADDED: Update empty flag safely on clock edge
        end
    end

    assign b_raddr = b_rptr[ADDR_WIDTH-1:0];

endmodule

RTL/write_ptr.v

module write_handler #(
    parameter DEPTH = 16,
    parameter ADDR_WIDTH = $clog2(DEPTH)
)(
    input wire wclk, 
    input wire wrst_n, 
    input wire w_en, 
    input wire [ADDR_WIDTH:0] g_rptr_sync, 
    
    output wire [ADDR_WIDTH-1:0] b_waddr,  
    output reg [ADDR_WIDTH:0] g_wptr,      
    output reg full // <-- CHANGED: Now a registered output
);

    reg  [ADDR_WIDTH:0] b_wptr;
    wire [ADDR_WIDTH:0] b_wptr_next;
    wire [ADDR_WIDTH:0] g_wptr_next;
    wire full_next; // <-- ADDED: Combinational full calculation

    // Binary next state
    assign b_wptr_next = b_wptr + (w_en & ~full);
    
    // Binary to Gray conversion
    assign g_wptr_next = (b_wptr_next >> 1) ^ b_wptr_next;

    // Full condition (Calculated combinationally based on next pointer)
    assign full_next = (g_wptr_next == {~g_rptr_sync[ADDR_WIDTH:ADDR_WIDTH-1], g_rptr_sync[ADDR_WIDTH-2:0]});

    always @(posedge wclk or negedge wrst_n) begin
        if (!wrst_n) begin
            b_wptr <= 0;
            g_wptr <= 0;
            full   <= 0; // <-- ADDED: Initialize full flag
        end else begin
            b_wptr <= b_wptr_next;
            g_wptr <= g_wptr_next;
            full   <= full_next; // <-- ADDED: Update full flag safely on clock edge
        end
    end

    assign b_waddr = b_wptr[ADDR_WIDTH-1:0];

endmodule

RTL/fifo_memory.v
module fifo_memory #(
    parameter DATA_WIDTH = 8, 
    parameter DEPTH = 16,
    parameter ADDR_WIDTH = $clog2(DEPTH)
)(
    input wire wclk, 
    input wire w_en, 
    input wire full,
    input wire [ADDR_WIDTH-1:0] w_addr,
    input wire [DATA_WIDTH-1:0] wdata,

    input wire rclk, 
    input wire r_en, 
    input wire empty,
    input wire [ADDR_WIDTH-1:0] r_addr,
    output reg [DATA_WIDTH-1:0] rdata
);

    reg [DATA_WIDTH-1:0] mem [0:DEPTH-1];
    
    // Write Operation
    always @(posedge wclk) begin
        if (w_en && !full) begin
            mem[w_addr] <= wdata;
        end
    end
    
    // Read Operation
    always @(posedge rclk) begin
        if (r_en && !empty) begin
            rdata <= mem[r_addr];
        end
        else if (r_en && empty) begin
            // NEW: Inject 'x's if an illegal read occurs
            rdata <= {DATA_WIDTH{1'bx}}; 
        end
    end
endmodule

RTL/Async_FIFO.v

`include "read_ptr.v"
`include "write_ptr.v"
`include "synchronize.v"
`include "fifo_memory.v"


module async_fifo #(
    parameter DATA_WIDTH = 8, 
    parameter DEPTH = 16
)(
    input wire wclk, rclk, wrst_n, rrst_n,
    input wire w_en, r_en,
    input wire [DATA_WIDTH-1:0] wdata,
    
    output wire [DATA_WIDTH-1:0] rdata,
    output wire full, empty
);

    localparam ADDR_WIDTH = $clog2(DEPTH);

    // Interconnect wires
    wire [ADDR_WIDTH-1:0] b_waddr, b_raddr;
    wire [ADDR_WIDTH:0]   g_wptr, g_rptr;
    wire [ADDR_WIDTH:0]   g_wptr_sync, g_rptr_sync;

    // 1. Memory Instantiation
    fifo_memory #(.DATA_WIDTH(DATA_WIDTH), .DEPTH(DEPTH)) mem_inst (
        .wclk(wclk), .w_en(w_en), .full(full), .w_addr(b_waddr), .wdata(wdata),
        .rclk(rclk), .r_en(r_en), .empty(empty), .r_addr(b_raddr), .rdata(rdata)
    );

    // 2. Write Domain Logic
    write_handler #(.DEPTH(DEPTH)) wr_inst (
        .wclk(wclk), .wrst_n(wrst_n), .w_en(w_en), .g_rptr_sync(g_rptr_sync),
        .b_waddr(b_waddr), .g_wptr(g_wptr), .full(full)
    );

    // 3. Read Domain Logic
    read_handler #(.DEPTH(DEPTH)) rd_inst (
        .rclk(rclk), .rrst_n(rrst_n), .r_en(r_en), .g_wptr_sync(g_wptr_sync),
        .b_raddr(b_raddr), .g_rptr(g_rptr), .empty(empty)
    );

    // 4. Synchronize Read Pointer into Write Domain
    synchronizer #(.WIDTH(ADDR_WIDTH + 1)) sync_r2w (
        .clk(wclk), .rst_n(wrst_n), .async_in(g_rptr), .sync_out(g_rptr_sync)
    );

    // 5. Synchronize Write Pointer into Read Domain
    synchronizer #(.WIDTH(ADDR_WIDTH + 1)) sync_w2r (
        .clk(rclk), .rst_n(rrst_n), .async_in(g_wptr), .sync_out(g_wptr_sync)
    );

endmodule

RTL/Testbench.v
`include "Async_FIFO.v"
`timescale 1ns/1ps

module tb_async_fifo;

    // Parameters matching the DUT
    parameter DATA_WIDTH = 8;
    parameter DEPTH = 16;

    // Testbench Signals
    reg wclk, rclk;
    reg wrst_n, rrst_n;
    reg w_en, r_en;
    reg [DATA_WIDTH-1:0] wdata;
    
    wire [DATA_WIDTH-1:0] rdata;
    wire full, empty;

    // -----------------------------------------------------------
    // 1. Device Under Test (DUT) Instantiation
    // -----------------------------------------------------------
    async_fifo #(
        .DATA_WIDTH(DATA_WIDTH),
        .DEPTH(DEPTH)
    ) dut (
        .wclk(wclk), 
        .rclk(rclk), 
        .wrst_n(wrst_n), 
        .rrst_n(rrst_n),
        .w_en(w_en), 
        .r_en(r_en),
        .wdata(wdata),
        .rdata(rdata),
        .full(full), 
        .empty(empty)
    );

    // -----------------------------------------------------------
    // 2. Clock Generation (Asynchronous Domains)
    // -----------------------------------------------------------
    // Write Clock: 100 MHz (10ns period)
    always #5 wclk = ~wclk;   

    // Read Clock: ~41.6 MHz (24ns period)
    // Using a strange frequency ensures clock edges slide past each other
    always #12 rclk = ~rclk;  

    // -----------------------------------------------------------
    // 3. Write and Read Tasks
    // -----------------------------------------------------------
    task write_word(input [DATA_WIDTH-1:0] data);
    begin
        @(posedge wclk);
        // Wait if the FIFO is full
        while (full) begin
            $display("[%0t] WRITE WAITING: FIFO is Full", $time);
            @(posedge wclk);
        end
        w_en  <= 1'b1;
        wdata <= data;
        
        @(posedge wclk);
        w_en  <= 1'b0;
        $display("[%0t] WROTE: %d", $time, data);
    end
    endtask

    task read_word();
    begin
        @(posedge rclk);
        // Wait if the FIFO is empty
        while (empty) begin
            $display("[%0t] READ WAITING: FIFO is Empty", $time);
            @(posedge rclk);
        end
        r_en <= 1'b1;
        
        @(posedge rclk);
        r_en <= 1'b0;
        // Wait 1ns for data to stabilize on the output port
        #1 $display("[%0t] READ : %d", $time, rdata);
    end
    endtask


    // -----------------------------------------------------------
    // 4. Main Simulation Sequence
    // -----------------------------------------------------------
    integer i;

    initial begin
        // Setup VCD dumping for waveform viewers (like GTKWave)
        $dumpfile("async_fifo.vcd");
        $dumpvars(0, tb_async_fifo);

        // Initialize all signals
        wclk = 0; rclk = 0;
        w_en = 0; r_en = 0;
        wdata = 0;
        
        // Assert Asynchronous Resets (Active Low)
        wrst_n = 0; rrst_n = 0;
        #30;
        
        // Release Resets safely on their respective clock edges
        @(negedge wclk) wrst_n = 1;
        @(negedge rclk) rrst_n = 1;
        #50;

        $display("\n=================================");
        $display(" PHASE 1: BURST WRITE TO FULL");
        $display("=================================");
        
        // FIX: Only write 16 words so we don't deadlock the sequential block!
        for (i = 0; i < 16; i = i + 1) begin
            write_word(i);
        end

        #100;

        $display("\n=================================");
        $display(" PHASE 2: BURST READ TO EMPTY");
        $display("=================================");
        // Read out all 16 items currently in the FIFO
        for (i = 0; i < 16; i = i + 1) begin
            read_word();
        end

        #100;

        $display("\n=================================");
        $display(" PHASE 3: CONCURRENT READ & WRITE");
        $display("=================================");
        // Fork-Join runs these two blocks simultaneously
        // Fork-Join runs these two blocks simultaneously
        fork
            begin : WRITE_THREAD
                // Using global integer 'i'
                for (i = 100; i < 150; i = i + 1) begin
                    write_word(i);
                    #($urandom % 10); 
                end
            end
            
            begin : READ_THREAD
                integer j; // <-- FIX: Declare a local integer for this thread
                // Using local integer 'j' so it doesn't fight with 'i'
                for (j = 0; j < 50; j = j + 1) begin
                    read_word();
                    #($urandom % 100);
                end
            end
        join

        $display("\n=================================");
        $display(" SIMULATION COMPLETE");
        $display("=================================");
        #100;
        $finish;
    end

    // Failsafe timeout just in case of an infinite loop
    initial begin
        #100000;
        $display("\nTIMEOUT EXCEEDED - FORCING SHUTDOWN");
        $finish;
    end

endmodule

RTL/async_fifo.vcd
$date
	Thu Apr  9 10:29:03 2026
$end
$version
	Icarus Verilog
$end
$timescale
	1ps
$end
$scope module tb_async_fifo $end
$var wire 8 ! rdata [7:0] $end
$var wire 1 " full $end
$var wire 1 # empty $end
$var parameter 32 $ DATA_WIDTH $end
$var parameter 32 % DEPTH $end
$var reg 1 & r_en $end
$var reg 1 ' rclk $end
$var reg 1 ( rrst_n $end
$var reg 1 ) w_en $end
$var reg 1 * wclk $end
$var reg 8 + wdata [7:0] $end
$var reg 1 , wrst_n $end
$var integer 32 - i [31:0] $end
$scope module dut $end
$var wire 1 & r_en $end
$var wire 1 ' rclk $end
$var wire 1 ( rrst_n $end
$var wire 1 ) w_en $end
$var wire 1 * wclk $end
$var wire 8 . wdata [7:0] $end
$var wire 1 , wrst_n $end
$var wire 8 / rdata [7:0] $end
$var wire 5 0 g_wptr_sync [4:0] $end
$var wire 5 1 g_wptr [4:0] $end
$var wire 5 2 g_rptr_sync [4:0] $end
$var wire 5 3 g_rptr [4:0] $end
$var wire 1 " full $end
$var wire 1 # empty $end
$var wire 4 4 b_waddr [3:0] $end
$var wire 4 5 b_raddr [3:0] $end
$var parameter 32 6 ADDR_WIDTH $end
$var parameter 32 7 DATA_WIDTH $end
$var parameter 32 8 DEPTH $end
$scope module mem_inst $end
$var wire 1 & r_en $end
$var wire 1 ' rclk $end
$var wire 1 ) w_en $end
$var wire 1 * wclk $end
$var wire 8 9 wdata [7:0] $end
$var wire 4 : w_addr [3:0] $end
$var wire 4 ; r_addr [3:0] $end
$var wire 1 " full $end
$var wire 1 # empty $end
$var parameter 32 < ADDR_WIDTH $end
$var parameter 32 = DATA_WIDTH $end
$var parameter 32 > DEPTH $end
$var reg 8 ? rdata [7:0] $end
$upscope $end
$scope module rd_inst $end
$var wire 5 @ g_rptr_next [4:0] $end
$var wire 1 & r_en $end
$var wire 1 ' rclk $end
$var wire 1 ( rrst_n $end
$var wire 5 A g_wptr_sync [4:0] $end
$var wire 1 B empty_next $end
$var wire 5 C b_rptr_next [4:0] $end
$var wire 4 D b_raddr [3:0] $end
$var parameter 32 E ADDR_WIDTH $end
$var parameter 32 F DEPTH $end
$var reg 5 G b_rptr [4:0] $end
$var reg 1 # empty $end
$var reg 5 H g_rptr [4:0] $end
$upscope $end
$scope module sync_r2w $end
$var wire 5 I async_in [4:0] $end
$var wire 1 * clk $end
$var wire 1 , rst_n $end
$var parameter 33 J WIDTH $end
$var reg 5 K q1 [4:0] $end
$var reg 5 L sync_out [4:0] $end
$upscope $end
$scope module sync_w2r $end
$var wire 1 ' clk $end
$var wire 1 ( rst_n $end
$var wire 5 M async_in [4:0] $end
$var parameter 33 N WIDTH $end
$var reg 5 O q1 [4:0] $end
$var reg 5 P sync_out [4:0] $end
$upscope $end
$scope module wr_inst $end
$var wire 5 Q g_rptr_sync [4:0] $end
$var wire 5 R g_wptr_next [4:0] $end
$var wire 1 ) w_en $end
$var wire 1 * wclk $end
$var wire 1 , wrst_n $end
$var wire 1 S full_next $end
$var wire 5 T b_wptr_next [4:0] $end
$var wire 4 U b_waddr [3:0] $end
$var parameter 32 V ADDR_WIDTH $end
$var parameter 32 W DEPTH $end
$var reg 5 X b_wptr [4:0] $end
$var reg 1 " full $end
$var reg 5 Y g_wptr [4:0] $end
$upscope $end
$upscope $end
$scope begin READ_THREAD $end
$var integer 32 Z j [31:0] $end
$upscope $end
$scope begin WRITE_THREAD $end
$upscope $end
$scope task read_word $end
$upscope $end
$scope task write_word $end
$var reg 8 [ data [7:0] $end
$upscope $end
$upscope $end
$enddefinitions $end
$comment Show the parameter values. $end
$dumpall
b10000 W
b100 V
b101 N
b101 J
b10000 F
b100 E
b10000 >
b1000 =
b100 <
b10000 8
b1000 7
b100 6
b10000 %
b1000 $
$end
#0
$dumpvars
bx [
bx Z
b0 Y
b0 X
b0 U
b0 T
0S
b0 R
b0 Q
b0 P
b0 O
b0 M
b0 L
b0 K
b0 I
b0 H
b0 G
b0 D
b0 C
1B
b0 A
b0 @
bx ?
b0 ;
b0 :
b0 9
b0 5
b0 4
b0 3
b0 2
b0 1
b0 0
bx /
b0 .
bx -
0,
b0 +
0*
0)
0(
0'
0&
1#
0"
bx !
$end
#5000
1*
#10000
0*
#12000
1'
#15000
1*
#20000
0*
#24000
0'
#25000
1*
#30000
1,
0*
#35000
1*
#36000
1'
#40000
0*
#45000
1*
#48000
1(
0'
#50000
0*
#55000
1*
#60000
0*
1'
#65000
1*
#70000
0*
#72000
0'
#75000
1*
#80000
0*
#84000
1'
#85000
1*
#90000
0*
#95000
1*
#96000
0'
#98000
b0 [
b0 -
#100000
0*
#105000
b1 R
b1 T
1)
1*
#108000
1'
#110000
0*
#115000
b1 R
b1 4
b1 :
b1 U
0)
b1 1
b1 M
b1 Y
b1 T
b1 X
b1 [
b1 -
1*
#120000
0*
0'
#125000
b11 R
b10 T
b1 +
b1 .
b1 9
1)
1*
#130000
0*
#132000
b1 O
1'
#135000
b11 R
b10 4
b10 :
b10 U
0)
b11 1
b11 M
b11 Y
b10 T
b10 X
b10 [
b10 -
1*
#140000
0*
#144000
0'
#145000
b10 R
b11 T
b10 +
b10 .
b10 9
1)
1*
#150000
0*
#155000
b10 R
b11 4
b11 :
b11 U
0)
b10 1
b10 M
b10 Y
b11 T
b11 X
b11 [
b11 -
1*
#156000
0B
b1 0
b1 A
b1 P
b10 O
1'
#160000
0*
#165000
b110 R
b100 T
b11 +
b11 .
b11 9
1)
1*
#168000
0'
#170000
0*
#175000
b110 R
b100 4
b100 :
b100 U
0)
b110 1
b110 M
b110 Y
b100 T
b100 X
b100 [
b100 -
1*
#180000
0#
b10 0
b10 A
b10 P
b110 O
0*
1'
#185000
b111 R
b101 T
b100 +
b100 .
b100 9
1)
1*
#190000
0*
#192000
0'
#195000
b111 R
b101 4
b101 :
b101 U
0)
b111 1
b111 M
b111 Y
b101 T
b101 X
b101 [
b101 -
1*
#200000
0*
#204000
b110 0
b110 A
b110 P
b111 O
1'
#205000
b101 R
b110 T
b101 +
b101 .
b101 9
1)
1*
#210000
0*
#215000
b101 R
b110 4
b110 :
b110 U
0)
b101 1
b101 M
b101 Y
b110 T
b110 X
b110 [
b110 -
1*
#216000
0'
#220000
0*
#225000
b100 R
b111 T
b110 +
b110 .
b110 9
1)
1*
#228000
b111 0
b111 A
b111 P
b101 O
1'
#230000
0*
#235000
b100 R
b111 4
b111 :
b111 U
0)
b100 1
b100 M
b100 Y
b111 T
b111 X
b111 [
b111 -
1*
#240000
0*
0'
#245000
b1100 R
b1000 T
b111 +
b111 .
b111 9
1)
1*
#250000
0*
#252000
b101 0
b101 A
b101 P
b100 O
1'
#255000
b1100 R
b1000 4
b1000 :
b1000 U
0)
b1100 1
b1100 M
b1100 Y
b1000 T
b1000 X
b1000 [
b1000 -
1*
#260000
0*
#264000
0'
#265000
b1101 R
b1001 T
b1000 +
b1000 .
b1000 9
1)
1*
#270000
0*
#275000
b1101 R
b1001 4
b1001 :
b1001 U
0)
b1101 1
b1101 M
b1101 Y
b1001 T
b1001 X
b1001 [
b1001 -
1*
#276000
b100 0
b100 A
b100 P
b1101 O
1'
#280000
0*
#285000
b1111 R
b1010 T
b1001 +
b1001 .
b1001 9
1)
1*
#288000
0'
#290000
0*
#295000
b1111 R
b1010 4
b1010 :
b1010 U
0)
b1111 1
b1111 M
b1111 Y
b1010 T
b1010 X
b1010 [
b1010 -
1*
#300000
b1101 0
b1101 A
b1101 P
b1111 O
0*
1'
#305000
b1110 R
b1011 T
b1010 +
b1010 .
b1010 9
1)
1*
#310000
0*
#312000
0'
#315000
b1110 R
b1011 4
b1011 :
b1011 U
0)
b1110 1
b1110 M
b1110 Y
b1011 T
b1011 X
b1011 [
b1011 -
1*
#320000
0*
#324000
b1111 0
b1111 A
b1111 P
b1110 O
1'
#325000
b1010 R
b1100 T
b1011 +
b1011 .
b1011 9
1)
1*
#330000
0*
#335000
b1010 R
b1100 4
b1100 :
b1100 U
0)
b1010 1
b1010 M
b1010 Y
b1100 T
b1100 X
b1100 [
b1100 -
1*
#336000
0'
#340000
0*
#345000
b1011 R
b1101 T
b1100 +
b1100 .
b1100 9
1)
1*
#348000
b1110 0
b1110 A
b1110 P
b1010 O
1'
#350000
0*
#355000
b1011 R
b1101 4
b1101 :
b1101 U
0)
b1011 1
b1011 M
b1011 Y
b1101 T
b1101 X
b1101 [
b1101 -
1*
#360000
0*
0'
#365000
b1001 R
b1110 T
b1101 +
b1101 .
b1101 9
1)
1*
#370000
0*
#372000
b1010 0
b1010 A
b1010 P
b1011 O
1'
#375000
b1001 R
b1110 4
b1110 :
b1110 U
0)
b1001 1
b1001 M
b1001 Y
b1110 T
b1110 X
b1110 [
b1110 -
1*
#380000
0*
#384000
0'
#385000
b1000 R
b1111 T
b1110 +
b1110 .
b1110 9
1)
1*
#390000
0*
#395000
b1000 R
b1111 4
b1111 :
b1111 U
0)
b1000 1
b1000 M
b1000 Y
b1111 T
b1111 X
b1111 [
b1111 -
1*
#396000
b1011 0
b1011 A
b1011 P
b1000 O
1'
#400000
0*
#405000
1S
b11000 R
b10000 T
b1111 +
b1111 .
b1111 9
1)
1*
#408000
0'
#410000
0*
#415000
1S
b11000 R
b0 4
b0 :
b0 U
0)
1"
b11000 1
b11000 M
b11000 Y
b10000 T
b10000 X
b10000 -
1*
#420000
b1000 0
b1000 A
b1000 P
b11000 O
0*
1'
#425000
1*
#430000
0*
#432000
0'
#435000
1*
#440000
0*
#444000
b11000 0
b11000 A
b11000 P
1'
#445000
1*
#450000
0*
#455000
1*
#456000
0'
#460000
0*
#465000
1*
#468000
1'
#470000
0*
#475000
1*
#480000
0*
0'
#485000
1*
#490000
0*
#492000
1'
#495000
1*
#500000
0*
#504000
0'
#505000
1*
#510000
0*
#515000
1*
b0 -
#516000
b1 @
b1 C
1&
1'
#520000
0*
#525000
1*
#528000
0'
#530000
0*
#535000
1*
#540000
b1 @
b1 5
b1 ;
b1 D
0&
b0 !
b0 /
b0 ?
b1 3
b1 H
b1 I
b1 C
b1 G
0*
1'
#541000
b1 -
#545000
b1 K
1*
#550000
0*
#552000
0'
#555000
0S
b1 2
b1 L
b1 Q
1*
#560000
0*
#564000
b11 @
b10 C
1&
1'
#565000
0"
1*
#570000
0*
#575000
1*
#576000
0'
#580000
0*
#585000
1*
#588000
b11 @
b10 5
b10 ;
b10 D
0&
b1 !
b1 /
b1 ?
b11 3
b11 H
b11 I
b10 C
b10 G
1'
#589000
b10 -
#590000
0*
#595000
b11 K
1*
#600000
0*
0'
#605000
b11 2
b11 L
b11 Q
1*
#610000
0*
#612000
b10 @
b11 C
1&
1'
#615000
1*
#620000
0*
#624000
0'
#625000
1*
#630000
0*
#635000
1*
#636000
b10 @
b11 5
b11 ;
b11 D
0&
b10 !
b10 /
b10 ?
b10 3
b10 H
b10 I
b11 C
b11 G
1'
#637000
b11 -
#640000
0*
#645000
b10 K
1*
#648000
0'
#650000
0*
#655000
b10 2
b10 L
b10 Q
1*
#660000
b110 @
b100 C
1&
0*
1'
#665000
1*
#670000
0*
#672000
0'
#675000
1*
#680000
0*
#684000
b110 @
b100 5
b100 ;
b100 D
0&
b11 !
b11 /
b11 ?
b110 3
b110 H
b110 I
b100 C
b100 G
1'
#685000
b110 K
b100 -
1*
#690000
0*
#695000
b110 2
b110 L
b110 Q
1*
#696000
0'
#700000
0*
#705000
1*
#708000
b111 @
b101 C
1&
1'
#710000
0*
#715000
1*
#720000
0*
0'
#725000
1*
#730000
0*
#732000
b111 @
b101 5
b101 ;
b101 D
0&
b100 !
b100 /
b100 ?
b111 3
b111 H
b111 I
b101 C
b101 G
1'
#733000
b101 -
#735000
b111 K
1*
#740000
0*
#744000
0'
#745000
b111 2
b111 L
b111 Q
1*
#750000
0*
#755000
1*
#756000
b101 @
b110 C
1&
1'
#760000
0*
#765000
1*
#768000
0'
#770000
0*
#775000
1*
#780000
b101 @
b110 5
b110 ;
b110 D
0&
b101 !
b101 /
b101 ?
b101 3
b101 H
b101 I
b110 C
b110 G
0*
1'
#781000
b110 -
#785000
b101 K
1*
#790000
0*
#792000
0'
#795000
b101 2
b101 L
b101 Q
1*
#800000
0*
#804000
b100 @
b111 C
1&
1'
#805000
1*
#810000
0*
#815000
1*
#816000
0'
#820000
0*
#825000
1*
#828000
b100 @
b111 5
b111 ;
b111 D
0&
b110 !
b110 /
b110 ?
b100 3
b100 H
b100 I
b111 C
b111 G
1'
#829000
b111 -
#830000
0*
#835000
b100 K
1*
#840000
0*
0'
#845000
b100 2
b100 L
b100 Q
1*
#850000
0*
#852000
b1100 @
b1000 C
1&
1'
#855000
1*
#860000
0*
#864000
0'
#865000
1*
#870000
0*
#875000
1*
#876000
b1100 @
b1000 5
b1000 ;
b1000 D
0&
b111 !
b111 /
b111 ?
b1100 3
b1100 H
b1100 I
b1000 C
b1000 G
1'
#877000
b1000 -
#880000
0*
#885000
b1100 K
1*
#888000
0'
#890000
0*
#895000
b1100 2
b1100 L
b1100 Q
1*
#900000
b1101 @
b1001 C
1&
0*
1'
#905000
1*
#910000
0*
#912000
0'
#915000
1*
#920000
0*
#924000
b1101 @
b1001 5
b1001 ;
b1001 D
0&
b1000 !
b1000 /
b1000 ?
b1101 3
b1101 H
b1101 I
b1001 C
b1001 G
1'
#925000
b1101 K
b1001 -
1*
#930000
0*
#935000
b1101 2
b1101 L
b1101 Q
1*
#936000
0'
#940000
0*
#945000
1*
#948000
b1111 @
b1010 C
1&
1'
#950000
0*
#955000
1*
#960000
0*
0'
#965000
1*
#970000
0*
#972000
b1111 @
b1010 5
b1010 ;
b1010 D
0&
b1001 !
b1001 /
b1001 ?
b1111 3
b1111 H
b1111 I
b1010 C
b1010 G
1'
#973000
b1010 -
#975000
b1111 K
1*
#980000
0*
#984000
0'
#985000
b1111 2
b1111 L
b1111 Q
1*
#990000
0*
#995000
1*
#996000
b1110 @
b1011 C
1&
1'
#1000000
0*
#1005000
1*
#1008000
0'
#1010000
0*
#1015000
1*
#1020000
b1110 @
b1011 5
b1011 ;
b1011 D
0&
b1010 !
b1010 /
b1010 ?
b1110 3
b1110 H
b1110 I
b1011 C
b1011 G
0*
1'
#1021000
b1011 -
#1025000
b1110 K
1*
#1030000
0*
#1032000
0'
#1035000
b1110 2
b1110 L
b1110 Q
1*
#1040000
0*
#1044000
b1010 @
b1100 C
1&
1'
#1045000
1*
#1050000
0*
#1055000
1*
#1056000
0'
#1060000
0*
#1065000
1*
#1068000
b1010 @
b1100 5
b1100 ;
b1100 D
0&
b1011 !
b1011 /
b1011 ?
b1010 3
b1010 H
b1010 I
b1100 C
b1100 G
1'
#1069000
b1100 -
#1070000
0*
#1075000
b1010 K
1*
#1080000
0*
0'
#1085000
b1010 2
b1010 L
b1010 Q
1*
#1090000
0*
#1092000
b1011 @
b1101 C
1&
1'
#1095000
1*
#1100000
0*
#1104000
0'
#1105000
1*
#1110000
0*
#1115000
1*
#1116000
b1011 @
b1101 5
b1101 ;
b1101 D
0&
b1100 !
b1100 /
b1100 ?
b1011 3
b1011 H
b1011 I
b1101 C
b1101 G
1'
#1117000
b1101 -
#1120000
0*
#1125000
b1011 K
1*
#1128000
0'
#1130000
0*
#1135000
b1011 2
b1011 L
b1011 Q
1*
#1140000
b1001 @
b1110 C
1&
0*
1'
#1145000
1*
#1150000
0*
#1152000
0'
#1155000
1*
#1160000
0*
#1164000
b1001 @
b1110 5
b1110 ;
b1110 D
0&
b1101 !
b1101 /
b1101 ?
b1001 3
b1001 H
b1001 I
b1110 C
b1110 G
1'
#1165000
b1001 K
b1110 -
1*
#1170000
0*
#1175000
b1001 2
b1001 L
b1001 Q
1*
#1176000
0'
#1180000
0*
#1185000
1*
#1188000
b1000 @
b1111 C
1&
1'
#1190000
0*
#1195000
1*
#1200000
0*
0'
#1205000
1*
#1210000
0*
#1212000
b1000 @
b1111 5
b1111 ;
b1111 D
0&
b1110 !
b1110 /
b1110 ?
b1000 3
b1000 H
b1000 I
b1111 C
b1111 G
1'
#1213000
b1111 -
#1215000
b1000 K
1*
#1220000
0*
#1224000
0'
#1225000
b1000 2
b1000 L
b1000 Q
1*
#1230000
0*
#1235000
1*
#1236000
1B
b11000 @
b10000 C
1&
1'
#1240000
0*
#1245000
1*
#1248000
0'
#1250000
0*
#1255000
1*
#1260000
1B
b11000 @
b0 5
b0 ;
b0 D
0&
b1111 !
b1111 /
b1111 ?
1#
b11000 3
b11000 H
b11000 I
b10000 C
b10000 G
0*
1'
#1261000
b10000 -
#1265000
b11000 K
1*
#1270000
0*
#1272000
0'
#1275000
b11000 2
b11000 L
b11000 Q
1*
#1280000
0*
#1284000
1'
#1285000
1*
#1290000
0*
#1295000
1*
#1296000
0'
#1300000
0*
#1305000
1*
#1308000
1'
#1310000
0*
#1315000
1*
#1320000
0*
0'
#1325000
1*
#1330000
0*
#1332000
1'
#1335000
1*
#1340000
0*
#1344000
0'
#1345000
1*
#1350000
0*
#1355000
1*
#1356000
1'
#1360000
0*
#1361000
b1100100 [
b1100100 -
b0 Z
#1365000
b11001 R
b10001 T
b1100100 +
b1100100 .
b1100100 9
1)
1*
#1368000
0'
#1370000
0*
#1375000
b11001 R
b1 4
b1 :
b1 U
0)
b11001 1
b11001 M
b11001 Y
b10001 T
b10001 X
1*
#1380000
b11001 O
0*
1'
#1381000
b1100101 [
b1100101 -
#1385000
b11011 R
b10010 T
b1100101 +
b1100101 .
b1100101 9
1)
1*
#1390000
0*
#1392000
0'
#1395000
b11011 R
b10 4
b10 :
b10 U
0)
b11011 1
b11011 M
b11011 Y
b10010 T
b10010 X
1*
#1400000
0*
#1404000
0B
b11001 0
b11001 A
b11001 P
b11011 O
b1100110 [
b1100110 -
1'
#1405000
b11010 R
b10011 T
b1100110 +
b1100110 .
b1100110 9
1)
1*
#1410000
0*
#1415000
b11010 R
b11 4
b11 :
b11 U
0)
b11010 1
b11010 M
b11010 Y
b10011 T
b10011 X
1*
#1416000
0'
#1420000
0*
#1424000
b1100111 [
b1100111 -
#1425000
b11110 R
b10100 T
b1100111 +
b1100111 .
b1100111 9
1)
1*
#1428000
0#
b11011 0
b11011 A
b11011 P
b11010 O
1'
#1430000
0*
#1435000
b11110 R
b100 4
b100 :
b100 U
0)
b11110 1
b11110 M
b11110 Y
b10100 T
b10100 X
1*
#1440000
0*
0'
#1444000
b1101000 [
b1101000 -
#1445000
b11111 R
b10101 T
b1101000 +
b1101000 .
b1101000 9
1)
1*
#1450000
0*
#1452000
b11001 @
b10001 C
1&
b11010 0
b11010 A
b11010 P
b11110 O
1'
#1455000
b11111 R
b101 4
b101 :
b101 U
0)
b11111 1
b11111 M
b11111 Y
b10101 T
b10101 X
1*
#1460000
b1101001 [
b1101001 -
0*
#1464000
0'
#1465000
b11101 R
b10110 T
b1101001 +
b1101001 .
b1101001 9
1)
1*
#1470000
0*
#1475000
b11101 R
b110 4
b110 :
b110 U
0)
b11101 1
b11101 M
b11101 Y
b10110 T
b10110 X
1*
#1476000
b11001 @
b1 5
b1 ;
b1 D
b1100100 !
b1100100 /
b1100100 ?
0&
b11001 3
b11001 H
b11001 I
b10001 C
b10001 G
b11110 0
b11110 A
b11110 P
b11101 O
1'
#1480000
b1101010 [
b1101010 -
0*
#1485000
b11100 R
b10111 T
b1101010 +
b1101010 .
b1101010 9
1)
b11001 K
1*
#1488000
0'
#1490000
0*
#1495000
b11100 R
b111 4
b111 :
b111 U
0)
b11100 1
b11100 M
b11100 Y
b10111 T
b10111 X
b11001 2
b11001 L
b11001 Q
1*
#1499000
b1101011 [
b1101011 -
#1500000
b11101 0
b11101 A
b11101 P
b11100 O
0*
1'
#1505000
b10100 R
b11000 T
b1101011 +
b1101011 .
b1101011 9
1)
1*
#1510000
0*
#1512000
0'
#1515000
b10100 R
b1000 4
b1000 :
b1000 U
0)
b10100 1
b10100 M
b10100 Y
b11000 T
b11000 X
1*
#1520000
0*
